{
  "tasks": [
    {
      "id": "Fri Jan 31 2025 16:15:00 GMT+0300",
      "title": "Приветик ",
      "description": "Описание ",
      "locationDescription": "Локация ",
      "location": {
        "latitude": 55.506227962657796,
        "longitude": 28.747593350708485
      },
      "synced": true,
      "updated": "Thu Jan 23 2025 14:59:59 GMT+0300",
      "markerLocation": {
        "latitude": 55.506227962657796,
        "longitude": 28.747593350708485
      },
      "file": [],
      "deleted": false,
      "deadLine": "2025-01-31T13:15:00.000Z"
    }
  ]
}